{
  "id_nil": 19,
  "nil": "PADOVA - TURRO - CRESCENZAGO",
  "nil_norm": "PADOVA - TURRO - CRESCENZAGO",
  "area_km2": 2.061867450298829,
  "popolazione_totale": 37409,
  "pct_stranieri": 34.99959902697212,
  "densita_abitanti_km2": 18143.261340382607,
  "famiglie_registrate": 21042,
  "famiglie_unipersonali": 12203,
  "nati_vivi": 245,
  "morti": 372,
  "immigrati": 1317,
  "emigrati": 1263,
  "saldo_naturale": -127,
  "saldo_migratorio": 54,
  "saldo_totale": -73,
  "nuovi_fabbricati_residenziali": 20,
  "abitazioni_nuove": 499,
  "numero_scuole": null,
  "numero_mercati": 3,
  "indice_verde_medio": 6.332307329712551,
  "comp_verde": 16.598120904205654,
  "comp_mercati": 60,
  "comp_densita": 32.19592693276505,
  "comp_dinamica": 40.022805017103764,
  "indice_qualita_vita": 35.0341192587289,
  "cluster_id": 2,
  "cluster_nome": "Urbano Denso",
  "cluster_colore": "#f59e0b",
  "ranking": {
    "ranking_iqv": 66,
    "ranking_verde": 45,
    "ranking_popolazione": 5
  }
}
