{
  "id_nil": 39,
  "nil": "QUINTOSOLE",
  "nil_norm": "QUINTOSOLE",
  "area_km2": 1.0585251045138209,
  "popolazione_totale": 935,
  "pct_stranieri": 16.149732620320854,
  "densita_abitanti_km2": 883.3045111664538,
  "famiglie_registrate": 794,
  "famiglie_unipersonali": 89,
  "nati_vivi": 1,
  "morti": 6,
  "immigrati": 82,
  "emigrati": 72,
  "saldo_naturale": -5,
  "saldo_migratorio": 10,
  "saldo_totale": 5,
  "nuovi_fabbricati_residenziali": null,
  "abitazioni_nuove": null,
  "numero_scuole": null,
  "numero_mercati": 0,
  "indice_verde_medio": 9.269458107387837,
  "comp_verde": 28.401809790307635,
  "comp_mercati": 0,
  "comp_densita": 96.6989593275359,
  "comp_dinamica": 48.91676168757127,
  "indice_qualita_vita": 44.92447319086909,
  "cluster_id": 1,
  "cluster_nome": "Residenziale Misto",
  "cluster_colore": "#22c55e",
  "ranking": {
    "ranking_iqv": 23,
    "ranking_verde": 28,
    "ranking_popolazione": 76
  }
}
